[
    {
        "name": "site_config",
        "type": "base",
        "system": false,
        "fields": [
            { "name": "company_name", "type": "text", "required": true, "presentable": true },
            { "name": "nib", "type": "text" },
            { "name": "address", "type": "text" },
            { "name": "phone_wa", "type": "text" },
            { "name": "email_official", "type": "email" },
            { "name": "welcome_text", "type": "editor" },
            { "name": "total_members", "type": "text" },
            { "name": "total_assets", "type": "text" }
        ],
        "listRule": "",
        "viewRule": "",
        "updateRule": "@request.auth.id != ''"
    },
    {
        "name": "news",
        "type": "base",
        "system": false,
        "fields": [
            { "name": "title", "type": "text", "required": true, "presentable": true },
            { "name": "slug", "type": "text", "required": true, "unique": true },
            { "name": "content", "type": "editor" },
            { "name": "thumbnail", "type": "file", "options": { "maxSelect": 1 } },
            { "name": "published", "type": "bool" },
            { "name": "category", "type": "select", "options": { "maxSelect": 1, "values": ["Berita", "Pengumuman", "Kegiatan"] } }
        ],
        "listRule": "",
        "viewRule": "",
        "createRule": "@request.auth.id != ''",
        "updateRule": "@request.auth.id != ''"
    },
    {
        "name": "hero_banners",
        "type": "base",
        "system": false,
        "fields": [
            { "name": "title", "type": "text", "required": true },
            { "name": "subtitle", "type": "text" },
            { "name": "image_desktop", "type": "file", "required": true, "options": { "maxSelect": 1 } },
            { "name": "active", "type": "bool" }
        ],
        "listRule": "",
        "viewRule": "",
        "createRule": "@request.auth.id != ''",
        "updateRule": "@request.auth.id != ''"
    },
    {
        "name": "perangkat_desa",
        "type": "base",
        "system": false,
        "fields": [
            { "name": "nama", "type": "text", "required": true, "presentable": true },
            { "name": "jabatan", "type": "text", "required": true },
            { "name": "nip", "type": "text" },
            { "name": "foto", "type": "file", "options": { "maxSelect": 1 } },
            { "name": "is_active", "type": "bool" }
        ],
        "listRule": "",
        "viewRule": "",
        "createRule": "@request.auth.id != ''",
        "updateRule": "@request.auth.id != ''"
    },
    {
        "name": "bku_transaksi",
        "type": "base",
        "system": false,
        "fields": [
            { "name": "type", "type": "select", "required": true, "options": { "maxSelect": 1, "values": ["masuk", "keluar", "pindah"] } },
            { "name": "amount", "type": "number", "required": true },
            { "name": "tanggal", "type": "date", "required": true },
            { "name": "uraian", "type": "text", "required": true },
            { "name": "bukti_foto", "type": "file", "options": { "maxSelect": 1 } }
        ],
        "listRule": "@request.auth.id != ''",
        "viewRule": "@request.auth.id != ''",
        "createRule": "@request.auth.id != ''",
        "updateRule": "@request.auth.id != ''"
    },
    {
        "name": "pajak_log",
        "type": "base",
        "system": false,
        "fields": [
            { "name": "bku_id", "type": "relation", "required": true, "options": { "collectionId": "pbc_bku", "maxSelect": 1 } },
            { "name": "jenis", "type": "select", "options": { "maxSelect": 1, "values": ["ppn", "pph"] } },
            { "name": "nominal", "type": "number", "required": true },
            { "name": "is_disetor", "type": "bool" }
        ],
        "listRule": "@request.auth.id != ''",
        "viewRule": "@request.auth.id != ''",
        "createRule": "@request.auth.id != ''",
        "updateRule": "@request.auth.id != ''"
    },
    {
        "name": "surat_keluar",
        "type": "base",
        "system": false,
        "fields": [
            { "name": "nomor_agenda", "type": "number" },
            { "name": "kode_surat", "type": "text", "required": true },
            { "name": "tujuan", "type": "text", "required": true },
            { "name": "tanggal_surat", "type": "date", "required": true }
        ],
        "listRule": "@request.auth.id != ''",
        "viewRule": "@request.auth.id != ''",
        "createRule": "@request.auth.id != ''",
        "updateRule": "@request.auth.id != ''"
    },
    {
        "name": "tanah_desa",
        "type": "base",
        "system": false,
        "fields": [
            { "name": "lokasi", "type": "text", "required": true },
            { "name": "luas_m2", "type": "number" },
            { "name": "pemegang_hak", "type": "text" }
        ],
        "listRule": "",
        "viewRule": "",
        "createRule": "@request.auth.id != ''",
        "updateRule": "@request.auth.id != ''"
    }
]
